{
  "name": "Manoonchai_Laos_Pali",
  "version": "1.0",
  "language": "Laos",
  "layers": ["Base", "Shift", "Command", "AltGr", "Control", "ShiftAltGr"],
  "license": "MIT",
  "os": {
    "windows": {
      "installerName": "LaosMnc",
      "company": "Manoonchai",
      "localeId": "0000042e"
    }
  },
  "keys": {
    "`": ["`", "~", "`", "`", "`", ""],
    "1": ["1", "!", "1", "໑", "1", "!"],
    "2": ["2", "@", "2", "໒", "2", "@"],
    "3": ["3", "#", "3", "໓", "3", "#"],
    "4": ["4", "$", "4", "໔", "4", "$"],
    "5": ["5", "%", "5", "໕", "5", "%"],
    "6": ["6", ",", "6", "໖", "6", "^"],
    "7": ["7", "&", "7", "໗", "7", "&"],
    "8": ["8", ".", "8", "໘", "8", "*"],
    "9": ["9", "(", "9", "໙", "9", ""],
    "0": ["0", ")", "0", "໐", "0", ""],
    "-": ["-", "_", "-", "÷", "-", ""],
    "=": ["=", "+", "=", "×", "=", ""],
    "q": ["ໃ", "ຒ", "q", "", "q", ""],
    "w": ["ຕ", "ຏ", "w", "x", "w", ""],
    "e": ["ຫ", "ຢ", "e", "໡", "e", ""],
    "r": ["ລ", "ຎ", "r", "໢", "r", ""],
    "t": ["ສ", "ຟ", "t", "", "t", ""],
    "y": ["ປ", "ຉ", "y", "", "y", ""],
    "u": ["ັ", "ຶ", "u", "຺", "u", ""],
    "i": ["ກ", "ຮ", "i", "ໞ", "i", ""],
    "o": ["ິ", "ຽ", "o", "", "o", ""],
    "p": ["ບ", "ຘ", "p", "", "p", ""],
    "[": ["ົ", "ຆ", "[", "[", "[", "{"],
    "]": ["ຬ", "ຑ", "]", "]", "]", "}"],
    "\\": ["ໆ", "ຯ", "\\", "\\", "\\", "|"],
    "a": ["ງ", "ຩ", "a", "໠", "a", ""],
    "s": ["ເ", "ຖ", "s", "◌", "s", ""],
    "d": ["ຣ", "ແ", "d", "₭", "d", ""],
    "f": ["ນ", "ຊ", "f", "ໜ", "f", ""],
    "g": ["ມ", "ພ", "g", "ໝ", "g", ""],
    "h": ["ອ", "ໍ", "h", "", "h", ""],
    "j": ["າ", "ຳ", "j", "", "j", ""],
    "k": ["່", "ຂ", "k", "຃", "k", ""],
    "l": ["້", "ໂ", "l", "໣", "l", ""],
    ";": ["ວ", "ຠ", ";", ";", ";", ":"],
    "'": ["ື", "\"", "'", "'", "'", "\""],
    "z": ["ຸ", "ຼ", "z", "຦", "z", ""],
    "x": ["ໄ", "ຝ", "x", "຤", "x", ""],
    "c": ["ທ", "ຜ", "c", "ຌ", "c", ""],
    "v": ["ຍ", "ຓ", "v", "ໟ", "v", ""],
    "b": ["ຈ", "໊", "b", "", "b", ""],
    "n": ["ຄ", "໋", "n", "຅", "n", ""],
    "m": ["ີ", "໌", "m", "໎", "m", ""],
    ",": ["ດ", "ຨ", ",", ",", ",", "<"],
    ".": ["ະ", "ຐ", ".", ".", ".", ">"],
    "/": ["ູ", "?", "/", "/", "/", "?"],
    " ": [" ", "\u200B", " ", " ", " ", " "],
    "KPDL": [",", ".", ",", ",", ",", ","]
  }
}
